tintalib/__init__.py
tintalib/tintalib.py
tintalib-0.1.dist-info/LICENSE
tintalib-0.1.dist-info/METADATA
tintalib-0.1.dist-info/WHEEL
tintalib-0.1.dist-info/top_level.txt
tintalib-0.1.dist-info/RECORD
