Metadata-Version: 2.1
Name: tintalib
Version: 0.1
Summary: tintalib is a Python library for adding text styling and colors to the terminal, supporting ANSI codes, RGB, and special effects like rainbow animations.
Home-page: https://github.com/managua48/tintalib
Author: Julio balladares
Author-email: julio.balladares@icloud.com
Classifier: Programming Language :: Python :: 3.6
Classifier: Programming Language :: Python :: 3.7
Classifier: Programming Language :: Python :: 3.8
Classifier: Programming Language :: Python :: 3.9
Classifier: Programming Language :: Python :: 3.10
Classifier: License :: OSI Approved :: MIT License
Classifier: Operating System :: OS Independent
Classifier: Intended Audience :: Developers
Classifier: Intended Audience :: System Administrators
Classifier: Topic :: Software Development :: Libraries :: Python Modules
Classifier: Topic :: Terminals
Classifier: Topic :: Utilities
Classifier: Topic :: System :: Logging
Classifier: Topic :: System :: Shells
Requires-Python: >=3.6
License-File: LICENSE
